actions/__init__.py
actions/email.py
actions/get_data.py
actions/optimiser.py
actions/r_code_python.py
tenorman-0.0.0.dist-info/METADATA
tenorman-0.0.0.dist-info/WHEEL
tenorman-0.0.0.dist-info/top_level.txt
tenorman-0.0.0.dist-info/RECORD
