Metadata-Version: 2.1
Name: tenorman
Version: 0.0.0
Summary: Tenorman is a Python package for tenor management.
Requires-Python: >=3.9
Requires-Dist: pandas ==2.1.1
Requires-Dist: numpy ==1.26.0
Requires-Dist: matplotlib ==3.8.0
Requires-Dist: scipy ==1.11.2
Requires-Dist: cvxpy ==1.3.2
Requires-Dist: O365 ==2.0.28
Requires-Dist: ccy ==1.3.1
